arcane/requests.py
arcane_requests-0.4.3.dist-info/METADATA
arcane_requests-0.4.3.dist-info/WHEEL
arcane_requests-0.4.3.dist-info/RECORD
