Metadata-Version: 2.3
Name: arcane-requests
Version: 0.4.3
Summary: Utility functions for requests
Author: Arcane
Author-email: product@wearcane.com
Requires-Python: >=3.7,<4.0
Classifier: Programming Language :: Python :: 3
Classifier: Programming Language :: Python :: 3.7
Classifier: Programming Language :: Python :: 3.8
Classifier: Programming Language :: Python :: 3.9
Classifier: Programming Language :: Python :: 3.10
Classifier: Programming Language :: Python :: 3.11
Classifier: Programming Language :: Python :: 3.12
Classifier: Programming Language :: Python :: 3.13
Requires-Dist: arcane-firebase (>=0.2.0,<0.3.0)
Requires-Dist: backoff (>=1.10.0)
Requires-Dist: google-auth (>=2.11,<3.0)
Requires-Dist: requests (>=2.23.0,<3.0.0)
Requires-Dist: typing-extensions (>=3.7)
